{
  "rust-analyzer.memoryUsage": true,
  "rust-analyzer.syntaxTree": true,
  "rust-analyzer.analyzerStatus": true,
  "rust-analyzer.reloadWorkspace": true,
  "rust-analyzer.run": true,
  "rust-analyzer.inlayHints.bindingModeHints.enable": false,
  "rust-analyzer.inlayHints.chainingHints.enable": false,
  "rust-analyzer.inlayHints.closingBraceHints.enable": false,
  "rust-analyzer.inlayHints.closureReturnTypeHints.enable": false,
  "rust-analyzer.inlayHints.parameterHints.enable": false,
  "rust-analyzer.inlayHints.typeHints.enable": false,
  "rust-analyzer.inlayHints.renderColons": false,
  "rust-analyzer.diagnostics.disabled": ["inactive-code"]
}
